{"total_count":1,"jobs":[{"id":8225133132,"run_id":3006609650,"run_url":"https://api.github.com/repos/apache/pulsar/actions/runs/3006609650","run_attempt":1,"node_id":"CR_kwDOA7PXtM8AAAAB6kGSTA","head_sha":"015e04510193659bc75924f91f35a8f7b21b0821","url":"https://api.github.com/repos/apache/pulsar/actions/jobs/8225133132","html_url":"https://github.com/apache/pulsar/runs/8225133132?check_suite_focus=true","status":"queued","conclusion":null,"started_at":"2022-09-07T09:41:59Z","completed_at":null,"name":"label","steps":[],"check_run_url":"https://api.github.com/repos/apache/pulsar/check-runs/8225133132","labels":["ubuntu-latest"],"runner_id":0,"runner_name":"","runner_group_id":0,"runner_group_name":""}]}