{"total_count":10,"jobs":[{"id":8193574413,"run_id":2994989787,"run_url":"https://api.github.com/repos/apache/pulsar/actions/runs/2994989787","run_attempt":1,"node_id":"CR_kwDOA7PXtM8AAAAB6GAGDQ","head_sha":"27ddb9eea878ad0e434b141aa2525aa25590f44d","url":"https://api.github.com/repos/apache/pulsar/actions/jobs/8193574413","html_url":"https://github.com/apache/pulsar/runs/8193574413?check_suite_focus=true","status":"completed","conclusion":"success","started_at":"2022-09-05T17:05:00Z","completed_at":"2022-09-05T17:05:07Z","name":"Changed files check","steps":[{"name":"Set up job","status":"completed","conclusion":"success","number":1,"started_at":"2022-09-05T19:04:59.000+02:00","completed_at":"2022-09-05T19:05:01.000+02:00"},{"name":"checkout","status":"completed","conclusion":"success","number":2,"started_at":"2022-09-05T19:05:01.000+02:00","completed_at":"2022-09-05T19:05:06.000+02:00"},{"name":"Detect changed files","status":"completed","conclusion":"success","number":3,"started_at":"2022-09-05T19:05:06.000+02:00","completed_at":"2022-09-05T19:05:06.000+02:00"},{"name":"Check changed files","status":"completed","conclusion":"success","number":4,"started_at":"2022-09-05T19:05:07.000+02:00","completed_at":"2022-09-05T19:05:07.000+02:00"},{"name":"Post checkout","status":"completed","conclusion":"success","number":8,"started_at":"2022-09-05T19:05:07.000+02:00","completed_at":"2022-09-05T19:05:07.000+02:00"},{"name":"Complete job","status":"completed","conclusion":"success","number":9,"started_at":"2022-09-05T19:05:06.000+02:00","completed_at":"2022-09-05T19:05:06.000+02:00"}],"check_run_url":"https://api.github.com/repos/apache/pulsar/check-runs/8193574413","labels":["ubuntu-20.04"],"runner_id":609,"runner_name":"GitHub Actions 165","runner_group_id":2,"runner_group_name":"GitHub Actions"},{"id":8193579319,"run_id":2994989787,"run_url":"https://api.github.com/repos/apache/pulsar/actions/runs/2994989787","run_attempt":1,"node_id":"CR_kwDOA7PXtM8AAAAB6GAZNw","head_sha":"27ddb9eea878ad0e434b141aa2525aa25590f44d","url":"https://api.github.com/repos/apache/pulsar/actions/jobs/8193579319","html_url":"https://github.com/apache/pulsar/runs/8193579319?check_suite_focus=true","status":"completed","conclusion":"failure","started_at":"2022-09-05T17:05:19Z","completed_at":"2022-09-05T17:06:34Z","name":"Build and License check","steps":[{"name":"Set up job","status":"completed","conclusion":"success","number":1,"started_at":"2022-09-05T19:05:18.000+02:00","completed_at":"2022-09-05T19:05:26.000+02:00"},{"name":"checkout","status":"completed","conclusion":"success","number":2,"started_at":"2022-09-05T19:05:26.000+02:00","completed_at":"2022-09-05T19:05:32.000+02:00"},{"name":"Tune Runner VM","status":"completed","conclusion":"success","number":3,"started_at":"2022-09-05T19:05:32.000+02:00","completed_at":"2022-09-05T19:05:37.000+02:00"},{"name":"Setup ssh access to build runner VM","status":"completed","conclusion":"skipped","number":4,"started_at":"2022-09-05T19:05:38.000+02:00","completed_at":"2022-09-05T19:05:38.000+02:00"},{"name":"Cache local Maven repository","status":"completed","conclusion":"success","number":5,"started_at":"2022-09-05T19:05:38.000+02:00","completed_at":"2022-09-05T19:05:47.000+02:00"},{"name":"Set up JDK 17","status":"completed","conclusion":"success","number":6,"started_at":"2022-09-05T19:05:48.000+02:00","completed_at":"2022-09-05T19:05:48.000+02:00"},{"name":"Check source code license headers","status":"completed","conclusion":"failure","number":7,"started_at":"2022-09-05T19:05:48.000+02:00","completed_at":"2022-09-05T19:06:31.000+02:00"},{"name":"Build core-modules","status":"completed","conclusion":"skipped","number":8,"started_at":"2022-09-05T19:06:31.000+02:00","completed_at":"2022-09-05T19:06:31.000+02:00"},{"name":"Check binary licenses","status":"completed","conclusion":"skipped","number":9,"started_at":"2022-09-05T19:06:31.000+02:00","completed_at":"2022-09-05T19:06:31.000+02:00"},{"name":"Install gh-actions-artifact-client.js","status":"completed","conclusion":"skipped","number":10,"started_at":"2022-09-05T19:06:31.000+02:00","completed_at":"2022-09-05T19:06:31.000+02:00"},{"name":"Save maven build results to Github artifact cache so that the results can be reused","status":"completed","conclusion":"skipped","number":11,"started_at":"2022-09-05T19:06:31.000+02:00","completed_at":"2022-09-05T19:06:31.000+02:00"},{"name":"Wait for ssh connection when build fails","status":"completed","conclusion":"skipped","number":12,"started_at":"2022-09-05T19:06:31.000+02:00","completed_at":"2022-09-05T19:06:31.000+02:00"},{"name":"Post Set up JDK 17","status":"completed","conclusion":"success","number":23,"started_at":"2022-09-05T19:06:31.000+02:00","completed_at":"2022-09-05T19:06:31.000+02:00"},{"name":"Post checkout","status":"completed","conclusion":"success","number":24,"started_at":"2022-09-05T19:06:34.000+02:00","completed_at":"2022-09-05T19:06:31.000+02:00"},{"name":"Complete job","status":"completed","conclusion":"success","number":26,"started_at":"2022-09-05T19:06:31.000+02:00","completed_at":"2022-09-05T19:06:31.000+02:00"},{"name":"Post Cache local Maven repository","status":"completed","conclusion":"skipped","number":27,"started_at":"2022-09-05T19:06:34.000+02:00","completed_at":"2022-09-05T19:06:31.000+02:00"}],"check_run_url":"https://api.github.com/repos/apache/pulsar/check-runs/8193579319","labels":["ubuntu-20.04"],"runner_id":609,"runner_name":"GitHub Actions 165","runner_group_id":2,"runner_group_name":"GitHub Actions"},{"id":8193600975,"run_id":2994989787,"run_url":"https://api.github.com/repos/apache/pulsar/actions/runs/2994989787","run_attempt":1,"node_id":"CR_kwDOA7PXtM8AAAAB6GBtzw","head_sha":"27ddb9eea878ad0e434b141aa2525aa25590f44d","url":"https://api.github.com/repos/apache/pulsar/actions/jobs/8193600975","html_url":"https://github.com/apache/pulsar/runs/8193600975?check_suite_focus=true","status":"completed","conclusion":"skipped","started_at":"2022-09-05T17:06:35Z","completed_at":"2022-09-05T17:06:35Z","name":"Build Pulsar java-test-image docker image","steps":[],"check_run_url":"https://api.github.com/repos/apache/pulsar/check-runs/8193600975","labels":[],"runner_id":null,"runner_name":null,"runner_group_id":null,"runner_group_name":null},{"id":8193601086,"run_id":2994989787,"run_url":"https://api.github.com/repos/apache/pulsar/actions/runs/2994989787","run_attempt":1,"node_id":"CR_kwDOA7PXtM8AAAAB6GBuPg","head_sha":"27ddb9eea878ad0e434b141aa2525aa25590f44d","url":"https://api.github.com/repos/apache/pulsar/actions/jobs/8193601086","html_url":"https://github.com/apache/pulsar/runs/8193601086?check_suite_focus=true","status":"completed","conclusion":"skipped","started_at":"2022-09-05T17:06:36Z","completed_at":"2022-09-05T17:06:36Z","name":"Build Pulsar docker image","steps":[],"check_run_url":"https://api.github.com/repos/apache/pulsar/check-runs/8193601086","labels":[],"runner_id":null,"runner_name":null,"runner_group_id":null,"runner_group_name":null},{"id":8193601225,"run_id":2994989787,"run_url":"https://api.github.com/repos/apache/pulsar/actions/runs/2994989787","run_attempt":1,"node_id":"CR_kwDOA7PXtM8AAAAB6GBuyQ","head_sha":"27ddb9eea878ad0e434b141aa2525aa25590f44d","url":"https://api.github.com/repos/apache/pulsar/actions/jobs/8193601225","html_url":"https://github.com/apache/pulsar/runs/8193601225?check_suite_focus=true","status":"completed","conclusion":"skipped","started_at":"2022-09-05T17:06:37Z","completed_at":"2022-09-05T17:06:37Z","name":"CI - Unit - ${{ matrix.name }}","steps":[],"check_run_url":"https://api.github.com/repos/apache/pulsar/check-runs/8193601225","labels":[],"runner_id":null,"runner_name":null,"runner_group_id":null,"runner_group_name":null},{"id":8193601362,"run_id":2994989787,"run_url":"https://api.github.com/repos/apache/pulsar/actions/runs/2994989787","run_attempt":1,"node_id":"CR_kwDOA7PXtM8AAAAB6GBvUg","head_sha":"27ddb9eea878ad0e434b141aa2525aa25590f44d","url":"https://api.github.com/repos/apache/pulsar/actions/jobs/8193601362","html_url":"https://github.com/apache/pulsar/runs/8193601362?check_suite_focus=true","status":"completed","conclusion":"skipped","started_at":"2022-09-05T17:06:37Z","completed_at":"2022-09-05T17:06:37Z","name":"CI - System - ${{ matrix.name }}","steps":[],"check_run_url":"https://api.github.com/repos/apache/pulsar/check-runs/8193601362","labels":[],"runner_id":null,"runner_name":null,"runner_group_id":null,"runner_group_name":null},{"id":8193601552,"run_id":2994989787,"run_url":"https://api.github.com/repos/apache/pulsar/actions/runs/2994989787","run_attempt":1,"node_id":"CR_kwDOA7PXtM8AAAAB6GBwEA","head_sha":"27ddb9eea878ad0e434b141aa2525aa25590f44d","url":"https://api.github.com/repos/apache/pulsar/actions/jobs/8193601552","html_url":"https://github.com/apache/pulsar/runs/8193601552?check_suite_focus=true","status":"completed","conclusion":"skipped","started_at":"2022-09-05T17:06:38Z","completed_at":"2022-09-05T17:06:38Z","name":"CI - Integration - ${{ matrix.name }}","steps":[],"check_run_url":"https://api.github.com/repos/apache/pulsar/check-runs/8193601552","labels":[],"runner_id":null,"runner_name":null,"runner_group_id":null,"runner_group_name":null},{"id":8193601717,"run_id":2994989787,"run_url":"https://api.github.com/repos/apache/pulsar/actions/runs/2994989787","run_attempt":1,"node_id":"CR_kwDOA7PXtM8AAAAB6GBwtQ","head_sha":"27ddb9eea878ad0e434b141aa2525aa25590f44d","url":"https://api.github.com/repos/apache/pulsar/actions/jobs/8193601717","html_url":"https://github.com/apache/pulsar/runs/8193601717?check_suite_focus=true","status":"completed","conclusion":"skipped","started_at":"2022-09-05T17:06:38Z","completed_at":"2022-09-05T17:06:38Z","name":"Delete system test docker image artifact","steps":[],"check_run_url":"https://api.github.com/repos/apache/pulsar/check-runs/8193601717","labels":[],"runner_id":null,"runner_name":null,"runner_group_id":null,"runner_group_name":null},{"id":8193601898,"run_id":2994989787,"run_url":"https://api.github.com/repos/apache/pulsar/actions/runs/2994989787","run_attempt":1,"node_id":"CR_kwDOA7PXtM8AAAAB6GBxag","head_sha":"27ddb9eea878ad0e434b141aa2525aa25590f44d","url":"https://api.github.com/repos/apache/pulsar/actions/jobs/8193601898","html_url":"https://github.com/apache/pulsar/runs/8193601898?check_suite_focus=true","status":"completed","conclusion":"skipped","started_at":"2022-09-05T17:06:39Z","completed_at":"2022-09-05T17:06:39Z","name":"Delete integration test docker image artifact","steps":[],"check_run_url":"https://api.github.com/repos/apache/pulsar/check-runs/8193601898","labels":[],"runner_id":null,"runner_name":null,"runner_group_id":null,"runner_group_name":null},{"id":8193602099,"run_id":2994989787,"run_url":"https://api.github.com/repos/apache/pulsar/actions/runs/2994989787","run_attempt":1,"node_id":"CR_kwDOA7PXtM8AAAAB6GByMw","head_sha":"27ddb9eea878ad0e434b141aa2525aa25590f44d","url":"https://api.github.com/repos/apache/pulsar/actions/jobs/8193602099","html_url":"https://github.com/apache/pulsar/runs/8193602099?check_suite_focus=true","status":"completed","conclusion":"skipped","started_at":"2022-09-05T17:06:39Z","completed_at":"2022-09-05T17:06:39Z","name":"Delete pulsar-maven-repository-binaries.tar.zst artifact","steps":[],"check_run_url":"https://api.github.com/repos/apache/pulsar/check-runs/8193602099","labels":[],"runner_id":null,"runner_name":null,"runner_group_id":null,"runner_group_name":null}]}