{"total_count":1,"jobs":[{"id":8199872775,"run_id":2997639499,"run_url":"https://api.github.com/repos/apache/pulsar/actions/runs/2997639499","run_attempt":1,"node_id":"CR_kwDOA7PXtM8AAAAB6MAhBw","head_sha":"00bb1b71d5452b1b46a4ee434cc0e2784854d954","url":"https://api.github.com/repos/apache/pulsar/actions/jobs/8199872775","html_url":"https://github.com/apache/pulsar/runs/8199872775?check_suite_focus=true","status":"completed","conclusion":"success","started_at":"2022-09-06T05:21:30Z","completed_at":"2022-09-06T05:42:46Z","name":"cpp-tests","steps":[{"name":"Set up job","status":"completed","conclusion":"success","number":1,"started_at":"2022-09-06T07:21:30.000+02:00","completed_at":"2022-09-06T07:21:33.000+02:00"},{"name":"checkout","status":"completed","conclusion":"success","number":2,"started_at":"2022-09-06T07:21:33.000+02:00","completed_at":"2022-09-06T07:21:38.000+02:00"},{"name":"Tune Runner VM","status":"completed","conclusion":"success","number":3,"started_at":"2022-09-06T07:21:39.000+02:00","completed_at":"2022-09-06T07:21:43.000+02:00"},{"name":"Detect changed files","status":"completed","conclusion":"success","number":4,"started_at":"2022-09-06T07:21:43.000+02:00","completed_at":"2022-09-06T07:21:43.000+02:00"},{"name":"Check changed files","status":"completed","conclusion":"success","number":5,"started_at":"2022-09-06T07:21:43.000+02:00","completed_at":"2022-09-06T07:21:43.000+02:00"},{"name":"Cache local Maven repository","status":"completed","conclusion":"success","number":6,"started_at":"2022-09-06T07:21:43.000+02:00","completed_at":"2022-09-06T07:21:49.000+02:00"},{"name":"Set up JDK 17","status":"completed","conclusion":"success","number":7,"started_at":"2022-09-06T07:21:49.000+02:00","completed_at":"2022-09-06T07:21:49.000+02:00"},{"name":"clean disk","status":"completed","conclusion":"success","number":8,"started_at":"2022-09-06T07:21:49.000+02:00","completed_at":"2022-09-06T07:21:56.000+02:00"},{"name":"build package","status":"completed","conclusion":"success","number":9,"started_at":"2022-09-06T07:21:57.000+02:00","completed_at":"2022-09-06T07:29:10.000+02:00"},{"name":"build cpp artifacts","status":"completed","conclusion":"success","number":10,"started_at":"2022-09-06T07:29:10.000+02:00","completed_at":"2022-09-06T07:38:10.000+02:00"},{"name":"run c++ tests","status":"completed","conclusion":"success","number":11,"started_at":"2022-09-06T07:38:11.000+02:00","completed_at":"2022-09-06T07:42:42.000+02:00"},{"name":"Upload test-logs","status":"completed","conclusion":"skipped","number":12,"started_at":"2022-09-06T07:42:43.000+02:00","completed_at":"2022-09-06T07:42:43.000+02:00"},{"name":"Post Set up JDK 17","status":"completed","conclusion":"success","number":23,"started_at":"2022-09-06T07:42:43.000+02:00","completed_at":"2022-09-06T07:42:43.000+02:00"},{"name":"Post Cache local Maven repository","status":"completed","conclusion":"success","number":24,"started_at":"2022-09-06T07:42:43.000+02:00","completed_at":"2022-09-06T07:42:45.000+02:00"},{"name":"Complete job","status":"completed","conclusion":"success","number":26,"started_at":"2022-09-06T07:42:46.000+02:00","completed_at":"2022-09-06T07:42:46.000+02:00"},{"name":"Post checkout","status":"completed","conclusion":"success","number":27,"started_at":"2022-09-06T07:42:46.000+02:00","completed_at":"2022-09-06T07:42:46.000+02:00"}],"check_run_url":"https://api.github.com/repos/apache/pulsar/check-runs/8199872775","labels":["ubuntu-latest"],"runner_id":821,"runner_name":"GitHub Actions 264","runner_group_id":2,"runner_group_name":"GitHub Actions"}]}