{"total_count":10,"jobs":[{"id":8203730447,"run_id":2999051044,"run_url":"https://api.github.com/repos/apache/pulsar/actions/runs/2999051044","run_attempt":1,"node_id":"CR_kwDOA7PXtM8AAAAB6Pr-Dw","head_sha":"ffbed5f6636abe470824035edbfb9ca3259e9808","url":"https://api.github.com/repos/apache/pulsar/actions/jobs/8203730447","html_url":"https://github.com/apache/pulsar/runs/8203730447?check_suite_focus=true","status":"completed","conclusion":"success","started_at":"2022-09-06T11:42:22Z","completed_at":"2022-09-06T11:42:32Z","name":"Changed files check","steps":[{"name":"Set up job","status":"completed","conclusion":"success","number":1,"started_at":"2022-09-06T13:42:21.000+02:00","completed_at":"2022-09-06T13:42:24.000+02:00"},{"name":"checkout","status":"completed","conclusion":"success","number":2,"started_at":"2022-09-06T13:42:24.000+02:00","completed_at":"2022-09-06T13:42:30.000+02:00"},{"name":"Detect changed files","status":"completed","conclusion":"success","number":3,"started_at":"2022-09-06T13:42:30.000+02:00","completed_at":"2022-09-06T13:42:30.000+02:00"},{"name":"Check changed files","status":"completed","conclusion":"success","number":4,"started_at":"2022-09-06T13:42:32.000+02:00","completed_at":"2022-09-06T13:42:32.000+02:00"},{"name":"Post checkout","status":"completed","conclusion":"success","number":8,"started_at":"2022-09-06T13:42:32.000+02:00","completed_at":"2022-09-06T13:42:32.000+02:00"},{"name":"Complete job","status":"completed","conclusion":"success","number":9,"started_at":"2022-09-06T13:42:31.000+02:00","completed_at":"2022-09-06T13:42:31.000+02:00"}],"check_run_url":"https://api.github.com/repos/apache/pulsar/check-runs/8203730447","labels":["ubuntu-20.04"],"runner_id":738,"runner_name":"GitHub Actions 181","runner_group_id":2,"runner_group_name":"GitHub Actions"},{"id":8205992921,"run_id":2999051044,"run_url":"https://api.github.com/repos/apache/pulsar/actions/runs/2999051044","run_attempt":1,"node_id":"CR_kwDOA7PXtM8AAAAB6R2D2Q","head_sha":"ffbed5f6636abe470824035edbfb9ca3259e9808","url":"https://api.github.com/repos/apache/pulsar/actions/jobs/8205992921","html_url":"https://github.com/apache/pulsar/runs/8205992921?check_suite_focus=true","status":"completed","conclusion":"cancelled","started_at":"2022-09-06T15:05:42Z","completed_at":"2022-09-06T15:05:42Z","name":"Build and License check","steps":[],"check_run_url":"https://api.github.com/repos/apache/pulsar/check-runs/8205992921","labels":["ubuntu-20.04"],"runner_id":0,"runner_name":"","runner_group_id":0,"runner_group_name":""},{"id":8210074139,"run_id":2999051044,"run_url":"https://api.github.com/repos/apache/pulsar/actions/runs/2999051044","run_attempt":1,"node_id":"CR_kwDOA7PXtM8AAAAB6VvKGw","head_sha":"ffbed5f6636abe470824035edbfb9ca3259e9808","url":"https://api.github.com/repos/apache/pulsar/actions/jobs/8210074139","html_url":"https://github.com/apache/pulsar/runs/8210074139?check_suite_focus=true","status":"completed","conclusion":"skipped","started_at":"2022-09-06T15:05:43Z","completed_at":"2022-09-06T15:05:43Z","name":"Build Pulsar docker image","steps":[],"check_run_url":"https://api.github.com/repos/apache/pulsar/check-runs/8210074139","labels":[],"runner_id":null,"runner_name":null,"runner_group_id":null,"runner_group_name":null},{"id":8210074361,"run_id":2999051044,"run_url":"https://api.github.com/repos/apache/pulsar/actions/runs/2999051044","run_attempt":1,"node_id":"CR_kwDOA7PXtM8AAAAB6VvK-Q","head_sha":"ffbed5f6636abe470824035edbfb9ca3259e9808","url":"https://api.github.com/repos/apache/pulsar/actions/jobs/8210074361","html_url":"https://github.com/apache/pulsar/runs/8210074361?check_suite_focus=true","status":"completed","conclusion":"skipped","started_at":"2022-09-06T15:05:44Z","completed_at":"2022-09-06T15:05:44Z","name":"CI - Unit - ${{ matrix.name }}","steps":[],"check_run_url":"https://api.github.com/repos/apache/pulsar/check-runs/8210074361","labels":[],"runner_id":null,"runner_name":null,"runner_group_id":null,"runner_group_name":null},{"id":8210074527,"run_id":2999051044,"run_url":"https://api.github.com/repos/apache/pulsar/actions/runs/2999051044","run_attempt":1,"node_id":"CR_kwDOA7PXtM8AAAAB6VvLnw","head_sha":"ffbed5f6636abe470824035edbfb9ca3259e9808","url":"https://api.github.com/repos/apache/pulsar/actions/jobs/8210074527","html_url":"https://github.com/apache/pulsar/runs/8210074527?check_suite_focus=true","status":"completed","conclusion":"skipped","started_at":"2022-09-06T15:05:45Z","completed_at":"2022-09-06T15:05:45Z","name":"Build Pulsar java-test-image docker image","steps":[],"check_run_url":"https://api.github.com/repos/apache/pulsar/check-runs/8210074527","labels":[],"runner_id":null,"runner_name":null,"runner_group_id":null,"runner_group_name":null},{"id":8210074707,"run_id":2999051044,"run_url":"https://api.github.com/repos/apache/pulsar/actions/runs/2999051044","run_attempt":1,"node_id":"CR_kwDOA7PXtM8AAAAB6VvMUw","head_sha":"ffbed5f6636abe470824035edbfb9ca3259e9808","url":"https://api.github.com/repos/apache/pulsar/actions/jobs/8210074707","html_url":"https://github.com/apache/pulsar/runs/8210074707?check_suite_focus=true","status":"completed","conclusion":"skipped","started_at":"2022-09-06T15:05:45Z","completed_at":"2022-09-06T15:05:45Z","name":"CI - Integration - ${{ matrix.name }}","steps":[],"check_run_url":"https://api.github.com/repos/apache/pulsar/check-runs/8210074707","labels":[],"runner_id":null,"runner_name":null,"runner_group_id":null,"runner_group_name":null},{"id":8210074882,"run_id":2999051044,"run_url":"https://api.github.com/repos/apache/pulsar/actions/runs/2999051044","run_attempt":1,"node_id":"CR_kwDOA7PXtM8AAAAB6VvNAg","head_sha":"ffbed5f6636abe470824035edbfb9ca3259e9808","url":"https://api.github.com/repos/apache/pulsar/actions/jobs/8210074882","html_url":"https://github.com/apache/pulsar/runs/8210074882?check_suite_focus=true","status":"completed","conclusion":"skipped","started_at":"2022-09-06T15:05:46Z","completed_at":"2022-09-06T15:05:46Z","name":"CI - System - ${{ matrix.name }}","steps":[],"check_run_url":"https://api.github.com/repos/apache/pulsar/check-runs/8210074882","labels":[],"runner_id":null,"runner_name":null,"runner_group_id":null,"runner_group_name":null},{"id":8210075094,"run_id":2999051044,"run_url":"https://api.github.com/repos/apache/pulsar/actions/runs/2999051044","run_attempt":1,"node_id":"CR_kwDOA7PXtM8AAAAB6VvN1g","head_sha":"ffbed5f6636abe470824035edbfb9ca3259e9808","url":"https://api.github.com/repos/apache/pulsar/actions/jobs/8210075094","html_url":"https://github.com/apache/pulsar/runs/8210075094?check_suite_focus=true","status":"completed","conclusion":"skipped","started_at":"2022-09-06T15:05:47Z","completed_at":"2022-09-06T15:05:47Z","name":"Delete integration test docker image artifact","steps":[],"check_run_url":"https://api.github.com/repos/apache/pulsar/check-runs/8210075094","labels":[],"runner_id":null,"runner_name":null,"runner_group_id":null,"runner_group_name":null},{"id":8210075274,"run_id":2999051044,"run_url":"https://api.github.com/repos/apache/pulsar/actions/runs/2999051044","run_attempt":1,"node_id":"CR_kwDOA7PXtM8AAAAB6VvOig","head_sha":"ffbed5f6636abe470824035edbfb9ca3259e9808","url":"https://api.github.com/repos/apache/pulsar/actions/jobs/8210075274","html_url":"https://github.com/apache/pulsar/runs/8210075274?check_suite_focus=true","status":"completed","conclusion":"skipped","started_at":"2022-09-06T15:05:47Z","completed_at":"2022-09-06T15:05:47Z","name":"Delete pulsar-maven-repository-binaries.tar.zst artifact","steps":[],"check_run_url":"https://api.github.com/repos/apache/pulsar/check-runs/8210075274","labels":[],"runner_id":null,"runner_name":null,"runner_group_id":null,"runner_group_name":null},{"id":8210075528,"run_id":2999051044,"run_url":"https://api.github.com/repos/apache/pulsar/actions/runs/2999051044","run_attempt":1,"node_id":"CR_kwDOA7PXtM8AAAAB6VvPiA","head_sha":"ffbed5f6636abe470824035edbfb9ca3259e9808","url":"https://api.github.com/repos/apache/pulsar/actions/jobs/8210075528","html_url":"https://github.com/apache/pulsar/runs/8210075528?check_suite_focus=true","status":"completed","conclusion":"skipped","started_at":"2022-09-06T15:05:48Z","completed_at":"2022-09-06T15:05:48Z","name":"Delete system test docker image artifact","steps":[],"check_run_url":"https://api.github.com/repos/apache/pulsar/check-runs/8210075528","labels":[],"runner_id":null,"runner_name":null,"runner_group_id":null,"runner_group_name":null}]}