{"total_count":1,"jobs":[{"id":8187248079,"run_id":2992738540,"run_url":"https://api.github.com/repos/apache/pulsar/actions/runs/2992738540","run_attempt":1,"node_id":"CR_kwDOA7PXtM8AAAAB5_99zw","head_sha":"87686b938038c36fbb92a24bcb4623241a3c8423","url":"https://api.github.com/repos/apache/pulsar/actions/jobs/8187248079","html_url":"https://github.com/apache/pulsar/runs/8187248079?check_suite_focus=true","status":"completed","conclusion":"success","started_at":"2022-09-05T11:26:08Z","completed_at":"2022-09-05T11:26:22Z","name":"owasp-dep-check","steps":[{"name":"Set up job","status":"completed","conclusion":"success","number":1,"started_at":"2022-09-05T13:26:08.000+02:00","completed_at":"2022-09-05T13:26:10.000+02:00"},{"name":"checkout","status":"completed","conclusion":"success","number":2,"started_at":"2022-09-05T13:26:10.000+02:00","completed_at":"2022-09-05T13:26:15.000+02:00"},{"name":"Tune Runner VM","status":"completed","conclusion":"success","number":3,"started_at":"2022-09-05T13:26:16.000+02:00","completed_at":"2022-09-05T13:26:20.000+02:00"},{"name":"Detect changed pom files","status":"completed","conclusion":"success","number":4,"started_at":"2022-09-05T13:26:21.000+02:00","completed_at":"2022-09-05T13:26:21.000+02:00"},{"name":"Cache local Maven repository","status":"completed","conclusion":"skipped","number":5,"started_at":"2022-09-05T13:26:22.000+02:00","completed_at":"2022-09-05T13:26:22.000+02:00"},{"name":"Set up JDK 17","status":"completed","conclusion":"skipped","number":6,"started_at":"2022-09-05T13:26:22.000+02:00","completed_at":"2022-09-05T13:26:22.000+02:00"},{"name":"clean disk","status":"completed","conclusion":"skipped","number":7,"started_at":"2022-09-05T13:26:22.000+02:00","completed_at":"2022-09-05T13:26:22.000+02:00"},{"name":"run \"clean verify\" to trigger dependency check","status":"completed","conclusion":"skipped","number":8,"started_at":"2022-09-05T13:26:22.000+02:00","completed_at":"2022-09-05T13:26:22.000+02:00"},{"name":"Upload report","status":"completed","conclusion":"skipped","number":9,"started_at":"2022-09-05T13:26:22.000+02:00","completed_at":"2022-09-05T13:26:22.000+02:00"},{"name":"Post checkout","status":"completed","conclusion":"success","number":18,"started_at":"2022-09-05T13:26:22.000+02:00","completed_at":"2022-09-05T13:26:22.000+02:00"},{"name":"Complete job","status":"completed","conclusion":"success","number":20,"started_at":"2022-09-05T13:26:21.000+02:00","completed_at":"2022-09-05T13:26:21.000+02:00"}],"check_run_url":"https://api.github.com/repos/apache/pulsar/check-runs/8187248079","labels":["ubuntu-latest"],"runner_id":466,"runner_name":"GitHub Actions 115","runner_group_id":2,"runner_group_name":"GitHub Actions"}]}