{"total_count":1,"jobs":[{"id":8220697776,"run_id":3004999125,"run_url":"https://api.github.com/repos/apache/pulsar/actions/runs/3004999125","run_attempt":1,"node_id":"CR_kwDOA7PXtM8AAAAB6f3ksA","head_sha":"c32eea9d0a397e74f80e2747dc7fbbd0d89a9d1c","url":"https://api.github.com/repos/apache/pulsar/actions/jobs/8220697776","html_url":"https://github.com/apache/pulsar/runs/8220697776?check_suite_focus=true","status":"completed","conclusion":"success","started_at":"2022-09-07T05:10:57Z","completed_at":"2022-09-07T05:16:20Z","name":"cpp-build-centos7","steps":[{"name":"Set up job","status":"completed","conclusion":"success","number":1,"started_at":"2022-09-07T07:10:57.000+02:00","completed_at":"2022-09-07T07:11:00.000+02:00"},{"name":"checkout","status":"completed","conclusion":"success","number":2,"started_at":"2022-09-07T07:11:00.000+02:00","completed_at":"2022-09-07T07:11:05.000+02:00"},{"name":"Tune Runner VM","status":"completed","conclusion":"success","number":3,"started_at":"2022-09-07T07:11:05.000+02:00","completed_at":"2022-09-07T07:11:10.000+02:00"},{"name":"Detect changed files","status":"completed","conclusion":"success","number":4,"started_at":"2022-09-07T07:11:10.000+02:00","completed_at":"2022-09-07T07:11:10.000+02:00"},{"name":"Check changed files","status":"completed","conclusion":"success","number":5,"started_at":"2022-09-07T07:11:11.000+02:00","completed_at":"2022-09-07T07:11:11.000+02:00"},{"name":"build cpp client on centos 7","status":"completed","conclusion":"success","number":6,"started_at":"2022-09-07T07:11:11.000+02:00","completed_at":"2022-09-07T07:16:18.000+02:00"},{"name":"Post checkout","status":"completed","conclusion":"success","number":12,"started_at":"2022-09-07T07:16:18.000+02:00","completed_at":"2022-09-07T07:16:18.000+02:00"},{"name":"Complete job","status":"completed","conclusion":"success","number":14,"started_at":"2022-09-07T07:16:18.000+02:00","completed_at":"2022-09-07T07:16:18.000+02:00"}],"check_run_url":"https://api.github.com/repos/apache/pulsar/check-runs/8220697776","labels":["ubuntu-latest"],"runner_id":835,"runner_name":"GitHub Actions 278","runner_group_id":2,"runner_group_name":"GitHub Actions"}]}