{"total_count":1,"jobs":[{"id":8204474240,"run_id":2999315189,"run_url":"https://api.github.com/repos/apache/pulsar/actions/runs/2999315189","run_attempt":1,"node_id":"CR_kwDOA7PXtM8AAAAB6QZXgA","head_sha":"ede4dd9bb5885248141102b9e4649504ee5fa836","url":"https://api.github.com/repos/apache/pulsar/actions/jobs/8204474240","html_url":"https://github.com/apache/pulsar/runs/8204474240?check_suite_focus=true","status":"completed","conclusion":"success","started_at":"2022-09-06T13:31:51Z","completed_at":"2022-09-06T13:52:25Z","name":"cpp-tests","steps":[{"name":"Set up job","status":"completed","conclusion":"success","number":1,"started_at":"2022-09-06T15:31:50.000+02:00","completed_at":"2022-09-06T15:31:53.000+02:00"},{"name":"checkout","status":"completed","conclusion":"success","number":2,"started_at":"2022-09-06T15:31:53.000+02:00","completed_at":"2022-09-06T15:31:58.000+02:00"},{"name":"Tune Runner VM","status":"completed","conclusion":"success","number":3,"started_at":"2022-09-06T15:31:59.000+02:00","completed_at":"2022-09-06T15:32:02.000+02:00"},{"name":"Detect changed files","status":"completed","conclusion":"success","number":4,"started_at":"2022-09-06T15:32:03.000+02:00","completed_at":"2022-09-06T15:32:03.000+02:00"},{"name":"Check changed files","status":"completed","conclusion":"success","number":5,"started_at":"2022-09-06T15:32:03.000+02:00","completed_at":"2022-09-06T15:32:03.000+02:00"},{"name":"Cache local Maven repository","status":"completed","conclusion":"success","number":6,"started_at":"2022-09-06T15:32:03.000+02:00","completed_at":"2022-09-06T15:32:07.000+02:00"},{"name":"Set up JDK 17","status":"completed","conclusion":"success","number":7,"started_at":"2022-09-06T15:32:08.000+02:00","completed_at":"2022-09-06T15:32:08.000+02:00"},{"name":"clean disk","status":"completed","conclusion":"success","number":8,"started_at":"2022-09-06T15:32:08.000+02:00","completed_at":"2022-09-06T15:32:36.000+02:00"},{"name":"build package","status":"completed","conclusion":"success","number":9,"started_at":"2022-09-06T15:32:36.000+02:00","completed_at":"2022-09-06T15:39:39.000+02:00"},{"name":"build cpp artifacts","status":"completed","conclusion":"success","number":10,"started_at":"2022-09-06T15:39:40.000+02:00","completed_at":"2022-09-06T15:47:58.000+02:00"},{"name":"run c++ tests","status":"completed","conclusion":"success","number":11,"started_at":"2022-09-06T15:47:58.000+02:00","completed_at":"2022-09-06T15:52:21.000+02:00"},{"name":"Upload test-logs","status":"completed","conclusion":"skipped","number":12,"started_at":"2022-09-06T15:52:22.000+02:00","completed_at":"2022-09-06T15:52:22.000+02:00"},{"name":"Post Set up JDK 17","status":"completed","conclusion":"success","number":23,"started_at":"2022-09-06T15:52:22.000+02:00","completed_at":"2022-09-06T15:52:22.000+02:00"},{"name":"Post checkout","status":"completed","conclusion":"success","number":24,"started_at":"2022-09-06T15:52:24.000+02:00","completed_at":"2022-09-06T15:52:24.000+02:00"},{"name":"Complete job","status":"completed","conclusion":"success","number":26,"started_at":"2022-09-06T15:52:24.000+02:00","completed_at":"2022-09-06T15:52:24.000+02:00"},{"name":"Post Cache local Maven repository","status":"completed","conclusion":"success","number":27,"started_at":"2022-09-06T15:52:22.000+02:00","completed_at":"2022-09-06T15:52:24.000+02:00"}],"check_run_url":"https://api.github.com/repos/apache/pulsar/check-runs/8204474240","labels":["ubuntu-latest"],"runner_id":788,"runner_name":"GitHub Actions 231","runner_group_id":2,"runner_group_name":"GitHub Actions"}]}