{"total_count":1,"jobs":[{"id":8220452307,"run_id":3004905059,"run_url":"https://api.github.com/repos/apache/pulsar/actions/runs/3004905059","run_attempt":1,"node_id":"CR_kwDOA7PXtM8AAAAB6fol0w","head_sha":"1ba1ba09db845606d0d0a451887c77c76de7f138","url":"https://api.github.com/repos/apache/pulsar/actions/jobs/8220452307","html_url":"https://github.com/apache/pulsar/runs/8220452307?check_suite_focus=true","status":"completed","conclusion":"success","started_at":"2022-09-07T04:24:41Z","completed_at":"2022-09-07T05:02:41Z","name":"owasp-dep-check","steps":[{"name":"Set up job","status":"completed","conclusion":"success","number":1,"started_at":"2022-09-07T06:24:40.000+02:00","completed_at":"2022-09-07T06:24:45.000+02:00"},{"name":"checkout","status":"completed","conclusion":"success","number":2,"started_at":"2022-09-07T06:24:46.000+02:00","completed_at":"2022-09-07T06:24:50.000+02:00"},{"name":"Tune Runner VM","status":"completed","conclusion":"success","number":3,"started_at":"2022-09-07T06:24:51.000+02:00","completed_at":"2022-09-07T06:24:55.000+02:00"},{"name":"Detect changed pom files","status":"completed","conclusion":"success","number":4,"started_at":"2022-09-07T06:24:55.000+02:00","completed_at":"2022-09-07T06:24:56.000+02:00"},{"name":"Cache local Maven repository","status":"completed","conclusion":"success","number":5,"started_at":"2022-09-07T06:24:56.000+02:00","completed_at":"2022-09-07T06:25:05.000+02:00"},{"name":"Set up JDK 17","status":"completed","conclusion":"success","number":6,"started_at":"2022-09-07T06:25:05.000+02:00","completed_at":"2022-09-07T06:25:05.000+02:00"},{"name":"clean disk","status":"completed","conclusion":"success","number":7,"started_at":"2022-09-07T06:25:06.000+02:00","completed_at":"2022-09-07T06:26:17.000+02:00"},{"name":"run \"clean verify\" to trigger dependency check","status":"completed","conclusion":"success","number":8,"started_at":"2022-09-07T06:26:19.000+02:00","completed_at":"2022-09-07T07:02:02.000+02:00"},{"name":"Upload report","status":"completed","conclusion":"skipped","number":9,"started_at":"2022-09-07T07:02:02.000+02:00","completed_at":"2022-09-07T07:02:02.000+02:00"},{"name":"Post Set up JDK 17","status":"completed","conclusion":"success","number":17,"started_at":"2022-09-07T07:02:02.000+02:00","completed_at":"2022-09-07T07:02:02.000+02:00"},{"name":"Post checkout","status":"completed","conclusion":"success","number":18,"started_at":"2022-09-07T07:02:41.000+02:00","completed_at":"2022-09-07T07:02:41.000+02:00"},{"name":"Complete job","status":"completed","conclusion":"success","number":20,"started_at":"2022-09-07T07:02:40.000+02:00","completed_at":"2022-09-07T07:02:40.000+02:00"},{"name":"Post Cache local Maven repository","status":"completed","conclusion":"success","number":21,"started_at":"2022-09-07T07:02:02.000+02:00","completed_at":"2022-09-07T07:02:40.000+02:00"}],"check_run_url":"https://api.github.com/repos/apache/pulsar/check-runs/8220452307","labels":["ubuntu-latest"],"runner_id":633,"runner_name":"GitHub Actions 146","runner_group_id":2,"runner_group_name":"GitHub Actions"}]}