{"total_count":3,"jobs":[{"id":8190851093,"run_id":2994003841,"run_url":"https://api.github.com/repos/apache/pulsar/actions/runs/2994003841","run_attempt":1,"node_id":"CR_kwDOA7PXtM8AAAAB6DZ4FQ","head_sha":"8eb16cf02c5b396554ba812de15db8911907695a","url":"https://api.github.com/repos/apache/pulsar/actions/jobs/8190851093","html_url":"https://github.com/apache/pulsar/runs/8190851093?check_suite_focus=true","status":"completed","conclusion":"success","started_at":"2022-09-05T15:32:31Z","completed_at":"2022-09-05T15:32:46Z","name":"Update Maven dependency cache for all modules","steps":[{"name":"Set up job","status":"completed","conclusion":"success","number":1,"started_at":"2022-09-05T17:32:31.000+02:00","completed_at":"2022-09-05T17:32:33.000+02:00"},{"name":"checkout","status":"completed","conclusion":"success","number":2,"started_at":"2022-09-05T17:32:33.000+02:00","completed_at":"2022-09-05T17:32:38.000+02:00"},{"name":"Tune Runner VM","status":"completed","conclusion":"success","number":3,"started_at":"2022-09-05T17:32:39.000+02:00","completed_at":"2022-09-05T17:32:43.000+02:00"},{"name":"Detect changed files","status":"completed","conclusion":"success","number":4,"started_at":"2022-09-05T17:32:43.000+02:00","completed_at":"2022-09-05T17:32:45.000+02:00"},{"name":"Cache local Maven repository","status":"completed","conclusion":"skipped","number":5,"started_at":"2022-09-05T17:32:46.000+02:00","completed_at":"2022-09-05T17:32:46.000+02:00"},{"name":"Set up JDK 17","status":"completed","conclusion":"skipped","number":6,"started_at":"2022-09-05T17:32:46.000+02:00","completed_at":"2022-09-05T17:32:46.000+02:00"},{"name":"Download dependencies","status":"completed","conclusion":"skipped","number":7,"started_at":"2022-09-05T17:32:46.000+02:00","completed_at":"2022-09-05T17:32:46.000+02:00"},{"name":"Post checkout","status":"completed","conclusion":"success","number":14,"started_at":"2022-09-05T17:32:46.000+02:00","completed_at":"2022-09-05T17:32:46.000+02:00"},{"name":"Complete job","status":"completed","conclusion":"success","number":16,"started_at":"2022-09-05T17:32:45.000+02:00","completed_at":"2022-09-05T17:32:45.000+02:00"}],"check_run_url":"https://api.github.com/repos/apache/pulsar/check-runs/8190851093","labels":["ubuntu-latest"],"runner_id":828,"runner_name":"GitHub Actions 271","runner_group_id":2,"runner_group_name":"GitHub Actions"},{"id":8190851231,"run_id":2994003841,"run_url":"https://api.github.com/repos/apache/pulsar/actions/runs/2994003841","run_attempt":1,"node_id":"CR_kwDOA7PXtM8AAAAB6DZ4nw","head_sha":"8eb16cf02c5b396554ba812de15db8911907695a","url":"https://api.github.com/repos/apache/pulsar/actions/jobs/8190851231","html_url":"https://github.com/apache/pulsar/runs/8190851231?check_suite_focus=true","status":"completed","conclusion":"success","started_at":"2022-09-05T15:32:00Z","completed_at":"2022-09-05T15:32:51Z","name":"Update Maven dependency cache for all modules - macos","steps":[{"name":"Set up job","status":"completed","conclusion":"success","number":1,"started_at":"2022-09-05T17:31:57.000+02:00","completed_at":"2022-09-05T17:32:29.000+02:00"},{"name":"checkout","status":"completed","conclusion":"success","number":2,"started_at":"2022-09-05T17:32:31.000+02:00","completed_at":"2022-09-05T17:32:45.000+02:00"},{"name":"Tune Runner VM","status":"completed","conclusion":"success","number":3,"started_at":"2022-09-05T17:32:47.000+02:00","completed_at":"2022-09-05T17:32:47.000+02:00"},{"name":"Detect changed files","status":"completed","conclusion":"success","number":4,"started_at":"2022-09-05T17:32:48.000+02:00","completed_at":"2022-09-05T17:32:48.000+02:00"},{"name":"Cache local Maven repository","status":"completed","conclusion":"skipped","number":5,"started_at":"2022-09-05T17:32:49.000+02:00","completed_at":"2022-09-05T17:32:46.000+02:00"},{"name":"Set up JDK 17","status":"completed","conclusion":"skipped","number":6,"started_at":"2022-09-05T17:32:49.000+02:00","completed_at":"2022-09-05T17:32:46.000+02:00"},{"name":"Download dependencies","status":"completed","conclusion":"skipped","number":7,"started_at":"2022-09-05T17:32:49.000+02:00","completed_at":"2022-09-05T17:32:46.000+02:00"},{"name":"Post checkout","status":"completed","conclusion":"success","number":14,"started_at":"2022-09-05T17:32:49.000+02:00","completed_at":"2022-09-05T17:32:49.000+02:00"},{"name":"Complete job","status":"completed","conclusion":"success","number":16,"started_at":"2022-09-05T17:32:47.000+02:00","completed_at":"2022-09-05T17:32:47.000+02:00"}],"check_run_url":"https://api.github.com/repos/apache/pulsar/check-runs/8190851231","labels":["macos-latest"],"runner_id":745,"runner_name":"GitHub Actions 188","runner_group_id":2,"runner_group_name":"GitHub Actions"},{"id":8190851407,"run_id":2994003841,"run_url":"https://api.github.com/repos/apache/pulsar/actions/runs/2994003841","run_attempt":1,"node_id":"CR_kwDOA7PXtM8AAAAB6DZ5Tw","head_sha":"8eb16cf02c5b396554ba812de15db8911907695a","url":"https://api.github.com/repos/apache/pulsar/actions/jobs/8190851407","html_url":"https://github.com/apache/pulsar/runs/8190851407?check_suite_focus=true","status":"completed","conclusion":"success","started_at":"2022-09-05T15:31:30Z","completed_at":"2022-09-05T15:31:44Z","name":"Update Maven dependency cache for core-modules","steps":[{"name":"Set up job","status":"completed","conclusion":"success","number":1,"started_at":"2022-09-05T17:31:30.000+02:00","completed_at":"2022-09-05T17:31:32.000+02:00"},{"name":"checkout","status":"completed","conclusion":"success","number":2,"started_at":"2022-09-05T17:31:32.000+02:00","completed_at":"2022-09-05T17:31:37.000+02:00"},{"name":"Tune Runner VM","status":"completed","conclusion":"success","number":3,"started_at":"2022-09-05T17:31:38.000+02:00","completed_at":"2022-09-05T17:31:42.000+02:00"},{"name":"Detect changed files","status":"completed","conclusion":"success","number":4,"started_at":"2022-09-05T17:31:42.000+02:00","completed_at":"2022-09-05T17:31:42.000+02:00"},{"name":"Cache local Maven repository","status":"completed","conclusion":"skipped","number":5,"started_at":"2022-09-05T17:31:44.000+02:00","completed_at":"2022-09-05T17:31:44.000+02:00"},{"name":"Set up JDK 17","status":"completed","conclusion":"skipped","number":6,"started_at":"2022-09-05T17:31:44.000+02:00","completed_at":"2022-09-05T17:31:44.000+02:00"},{"name":"Download dependencies","status":"completed","conclusion":"skipped","number":7,"started_at":"2022-09-05T17:31:44.000+02:00","completed_at":"2022-09-05T17:31:44.000+02:00"},{"name":"Post checkout","status":"completed","conclusion":"success","number":14,"started_at":"2022-09-05T17:31:44.000+02:00","completed_at":"2022-09-05T17:31:44.000+02:00"},{"name":"Complete job","status":"completed","conclusion":"success","number":16,"started_at":"2022-09-05T17:31:43.000+02:00","completed_at":"2022-09-05T17:31:43.000+02:00"}],"check_run_url":"https://api.github.com/repos/apache/pulsar/check-runs/8190851407","labels":["ubuntu-latest"],"runner_id":454,"runner_name":"GitHub Actions 103","runner_group_id":2,"runner_group_name":"GitHub Actions"}]}